portsort/__init__.py
portsort/portsort.py
portsort-0.2.4.dist-info/LICENSE
portsort-0.2.4.dist-info/METADATA
portsort-0.2.4.dist-info/WHEEL
portsort-0.2.4.dist-info/top_level.txt
portsort-0.2.4.dist-info/RECORD
