Metadata-Version: 2.1
Name: portsort
Version: 0.2.4
Summary: A package to sort stocks into portfolios and calculate weighted-average returns.
Home-page: https://github.com/ioannisrpt/portsort
Author: Ioannis Ropotos
Author-email: <ioannis.ropotos@ucdconnect.ie>
Keywords: python,finance,asset-pricing,portfolio,sort,stocks,returns
Classifier: Development Status :: 4 - Beta
Classifier: License :: OSI Approved :: GNU General Public License v3 (GPLv3)
Classifier: Intended Audience :: Science/Research
Classifier: Intended Audience :: Financial and Insurance Industry
Classifier: Programming Language :: Python :: 3.7
Classifier: Operating System :: Microsoft :: Windows
License-File: LICENSE
Requires-Dist: pandas (>=1.0.0)
Requires-Dist: numpy (>=1.0.0)
